AUTHORS.rst
LICENSE
MANIFEST.in
README.rst
requirements.txt
setup.cfg
setup.py
castroredux/__init__.py
castroredux/castroredux.py
castroredux.egg-info/PKG-INFO
castroredux.egg-info/SOURCES.txt
castroredux.egg-info/dependency_links.txt
castroredux.egg-info/not-zip-safe
castroredux.egg-info/requires.txt
castroredux.egg-info/top_level.txt
castroredux/tools/__init__.py
castroredux/tools/flvrec.py
castroredux/tools/vnc2flv/__init__.py
castroredux/tools/vnc2flv/audio.py
castroredux/tools/vnc2flv/d3des.py
castroredux/tools/vnc2flv/flv.py
castroredux/tools/vnc2flv/rfb.py
castroredux/tools/vnc2flv/video.py