Metadata-Version: 1.1
Name: castroredux
Version: 0.1.4
Summary: 'screencast robot' - a tiny fork of vnc2flv
Home-page: https://github.com/brome-hq/castroredux
Author: Brome-HQ
Author-email: brome.hq@gmail.com
License: ISCL
Keywords: castroredux
Platform: UNKNOWN
Classifier: Development Status :: 2 - Pre-Alpha
Classifier: Intended Audience :: Developers
Classifier: License :: OSI Approved :: ISC License (ISCL)
Classifier: Natural Language :: English
Classifier: Programming Language :: Python :: 2.6
Classifier: Programming Language :: Python :: 2.7
